Workbook
Name SAL_MIN: 'Parametros 2026'!$C$5
Name OT_MULT: 'Parametros 2026'!$C$6
Name MEAL_MULT: 'Parametros 2026'!$C$7
Name SS_PCT: 'Parametros 2026'!$C$8
Name SS_BASE: 'Parametros 2026'!$C$9
Name MED_PCT: 'Parametros 2026'!$C$10
Name MED_ADD: 'Parametros 2026'!$C$11
Name SINOT_PCT: 'Parametros 2026'!$C$12
Name SINOT_BASE: 'Parametros 2026'!$C$13
Name FUTA_PCT: 'Parametros 2026'!$C$14
Name SUTA_PCT: 'Parametros 2026'!$C$15
Name UI_BASE: 'Parametros 2026'!$C$16
Name CHOFER_WK: 'Parametros 2026'!$C$17
Name BONO_PCT_G: 'Parametros 2026'!$C$18
Name BONO_PCT_P: 'Parametros 2026'!$C$19
Name BONO_TOPE: 'Parametros 2026'!$C$20
Name BONO_HRS: 'Parametros 2026'!$C$21
Name RET_1099: 'Parametros 2026'!$C$22
Name EXEN_1099: 'Parametros 2026'!$C$23

Sheet Parametros 2026
A1: PARÁMETROS Y TASAS DE NÓMINA — 2026
A2: Empresas HC LLC · Puerto Rico · Edite SOLO las celdas amarillas. Todas las hojas leen estas tasas.
A4: SECCIÓN | B4: CONCEPTO | C4: VALOR | D4: NOTA / FUENTE
A5: Salario | B5: Salario mínimo por hora (PR) | C5: 10.5 | D5: Ley 47-2021. Vigente 2026: $10.50/h
A6: Salario | B6: Multiplicador horas extra | C6: 2 | D6: Ley 379-1948: >8h/día ó >40h/sem = 2x (doble)
A7: Salario | B7: Multiplicador período de comida trabajado | C7: 1.5 | D7: Ley 379: comida trabajada = 1.5x
A8: Seguro Social | B8: SS % (empleado y patrono c/u) | C8: 0.062 | D8: FICA federal 6.2% cada parte
A9: Seguro Social | B9: Base salarial anual SS | C9: 176100 | D9: Tope 2025=$176,100. VERIFICAR base 2026 (SSA)
A10: Medicare | B10: Medicare % (empleado y patrono c/u) | C10: 0.0145 | D10: FICA 1.45% cada parte (sin tope)
A11: Medicare | B11: Medicare adicional % (empleado) | C11: 0.009 | D11: 0.9% sobre exceso de $200,000 (solo empleado)
A12: SINOT | B12: SINOT % (empleado y patrono c/u) | C12: 0.003 | D12: 0.3% cada parte sobre primeros $9,000 (DTRH)
A13: SINOT | B13: Base salarial anual SINOT | C13: 9000 | D13: Primeros $9,000 del año
A14: Desempleo | B14: FUTA % neto (patrono) | C14: 0.006 | D14: 6% menos crédito 5.4% = 0.6% sobre $7,000
A15: Desempleo | B15: SUTA % (patrono) — TASA ASIGNADA | C15: 0.028 | D15: EDITAR: tasa que le asigna el DTRH a HC LLC
A16: Desempleo | B16: Base salarial anual desempleo | C16: 7000 | D16: Primeros $7,000 (FUTA/SUTA)
... A23: Contratistas | B23: Exención anual antes de retener | C23: 500 | D23: Primeros $500/año exentos por contratista

Sheet Nómina W-2
A1: REGISTRO DE NÓMINA — EMPLEADOS W-2
A2: Ingrese celdas amarillas (A–H, O). Columnas azules se calculan solas. Topes anuales aplicados con Bruto YTD anterior.
A3: Empleado | B3: ID/SSN (últ. 4) | C3: Puesto | D3: Fecha ingreso | E3: Tarifa/hora | F3: Horas reg. | G3: Horas extra (2x) | H3: Bruto YTD anterior | I3: Salario regular | J3: Pago horas extra | K3: BRUTO período | L3: Seg. Social (emp) | M3: Medicare (emp) | N3: SINOT (emp) | O3: Retención PR (499R) | P3: Total deducc. | Q3: NETO A PAGAR | R3: SS patrono | S3: Medicare patrono | T3: FUTA | U3: SUTA | V3: SINOT patrono | W3: COSTO PATRONAL TOTAL
A4: María Rodríguez (EJEMPLO) | B4: 1234 | C4: Administradora | D4: 2023-03-01 | E4: 18 | F4: 80 | G4: 5 | H4: 0 | I4: =E4*F4 | J4: =E4*OT_MULT*G4 | K4: =I4+J4 | L4: =MIN(K4,MAX(0,SS_BASE-H4))*SS_PCT | M4: =K4*MED_PCT | N4: =MIN(K4,MAX(0,SINOT_BASE-H4))*SINOT_PCT | O4: 0 | P4: =L4+M4+N4+O4 | Q4: =K4-P4 | R4: =MIN(K4,MAX(0,SS_BASE-H4))*SS_PCT | S4: =K4*MED_PCT | T4: =MIN(K4,MAX(0,UI_BASE-H4))*FUTA_PCT | U4: =MIN(K4,MAX(0,UI_BASE-H4))*SUTA_PCT | V4: =MIN(K4,MAX(0,SINOT_BASE-H4))*SINOT_PCT | W4: =K4+R4+S4+T4+U4+V4
A5: José Torres (EJEMPLO) | B5: 5678 | C5: Chofer/Reparto | D5: 2021-07-15 | E5: 12.5 | F5: 80 | G5: 8 | H5: 0 | I5: =E5*F5 | J5: =E5*OT_MULT*G5 | K5: =I5+J5 | L5: =MIN(K5,MAX(0,SS_BASE-H5))*SS_PCT | M5: =K5*MED_PCT | N5: =MIN(K5,MAX(0,SINOT_BASE-H5))*SINOT_PCT | O5: 0 | P5: =L5+M5+N5+O5 | Q5: =K5-P5 | R5: =MIN(K5,MAX(0,SS_BASE-H5))*SS_PCT | S5: =K5*MED_PCT | T5: =MIN(K5,MAX(0,UI_BASE-H5))*FUTA_PCT | U5: =MIN(K5,MAX(0,UI_BASE-H5))*SUTA_PCT | V5: =MIN(K5,MAX(0,SINOT_BASE-H5))*SINOT_PCT | W5: =K5+R5+S5+T5+U5+V5
A6: Ana Vega (EJEMPLO) | B6: 9012 | C6: Ventas | D6: 2024-01-10 | E6: 10.5 | F6: 72 | G6: 0 | H6: 0 | I6: =E6*F6 | J6: =E6*OT_MULT*G6 | K6: =I6+J6 | L6: =MIN(K6,MAX(0,SS_BASE-H6))*SS_PCT | M6: =K6*MED_PCT | N6: =MIN(K6,MAX(0,SINOT_BASE-H6))*SINOT_PCT | O6: 0 | P6: =L6+M6+N6+O6 | Q6: =K6-P6 | R6: =MIN(K6,MAX(0,SS_BASE-H6))*SS_PCT | S6: =K6*MED_PCT | T6: =MIN(K6,MAX(0,UI_BASE-H6))*FUTA_PCT | U6: =MIN(K6,MAX(0,UI_BASE-H6))*SUTA_PCT | V6: =MIN(K6,MAX(0,SINOT_BASE-H6))*SINOT_PCT | W6: =K6+R6+S6+T6+U6+V6
I7: =E7*F7 | J7: =E7*OT_MULT*G7 | K7: =I7+J7 | L7: =MIN(K7,MAX(0,SS_BASE-H7))*SS_PCT | M7: =K7*MED_PCT | N7: =MIN(K7,MAX(0,SINOT_BASE-H7))*SINOT_PCT | O7: 0 | P7: =L7+M7+N7+O7 | Q7: =K7-P7 | R7: =MIN(K7,MAX(0,SS_BASE-H7))*SS_PCT | S7: =K7*MED_PCT | T7: =MIN(K7,MAX(0,UI_BASE-H7))*FUTA_PCT | U7: =MIN(K7,MAX(0,UI_BASE-H7))*SUTA_PCT | V7: =MIN(K7,MAX(0,SINOT_BASE-H7))*SINOT_PCT | W7: =K7+R7+S7+T7+U7+V7
I8: =E8*F8 | J8: =E8*OT_MULT*G8 | K8: =I8+J8 | L8: =MIN(K8,MAX(0,SS_BASE-H8))*SS_PCT | M8: =K8*MED_PCT | N8: =MIN(K8,MAX(0,SINOT_BASE-H8))*SINOT_PCT | O8: 0 | P8: =L8+M8+N8+O8 | Q8: =K8-P8 | R8: =MIN(K8,MAX(0,SS_BASE-H8))*SS_PCT | S8: =K8*MED_PCT | T8: =MIN(K8,MAX(0,UI_BASE-H8))*FUTA_PCT | U8: =MIN(K8,MAX(0,UI_BASE-H8))*SUTA_PCT | V8: =MIN(K8,MAX(0,SINOT_BASE-H8))*SINOT_PCT | W8: =K8+R8+S8+T8+U8+V8
I9: =E9*F9 | J9: =E9*OT_MULT*G9 | K9: =I9+J9 | L9: =MIN(K9,MAX(0,SS_BASE-H9))*SS_PCT | M9: =K9*MED_PCT | N9: =MIN(K9,MAX(0,SINOT_BASE-H9))*SINOT_PCT | O9: 0 | P9: =L9+M9+N9+O9 | Q9: =K9-P9 | R9: =MIN(K9,MAX(0,SS_BASE-H9))*SS_PCT | S9: =K9*MED_PCT | T9: =MIN(K9,MAX(0,UI_BASE-H9))*FUTA_PCT | U9: =MIN(K9,MAX(0,UI_BASE-H9))*SUTA_PCT | V9: =MIN(K9,MAX(0,SINOT_BASE-H9))*SINOT_PCT | W9: =K9+R9+S9+T9+U9+V9
I10: =E10*F10 | J10: =E10*OT_MULT*G10 | K10: =I10+J10 | L10: =MIN(K10,MAX(0,SS_BASE-H10))*SS_PCT | M10: =K10*MED_PCT | N10: =MIN(K10,MAX(0,SINOT_BASE-H10))*SINOT_PCT | O10: 0 | P10: =L10+M10+N10+O10 | Q10: =K10-P10 | R10: =MIN(K10,MAX(0,SS_BASE-H10))*SS_PCT | S10: =K10*MED_PCT | T10: =MIN(K10,MAX(0,UI_BASE-H10))*FUTA_PCT | U10: =MIN(K10,MAX(0,UI_BASE-H10))*SUTA_PCT | V10: =MIN(K10,MAX(0,SINOT_BASE-H10))*SINOT_PCT | W10: =K10+R10+S10+T10+U10+V10
I11: =E11*F11 | J11: =E11*OT_MULT*G11 | K11: =I11+J11 | L11: =MIN(K11,MAX(0,SS_BASE-H11))*SS_PCT | M11: =K11*MED_PCT | N11: =MIN(K11,MAX(0,SINOT_BASE-H11))*SINOT_PCT | O11: 0 | P11: =L11+M11+N11+O11 | Q11: =K11-P11 | R11: =MIN(K11,MAX(0,SS_BASE-H11))*SS_PCT | S11: =K11*MED_PCT | T11: =MIN(K11,MAX(0,UI_BASE-H11))*FUTA_PCT | U11: =MIN(K11,MAX(0,UI_BASE-H11))*SUTA_PCT | V11: =MIN(K11,MAX(0,SINOT_BASE-H11))*SINOT_PCT | W11: =K11+R11+S11+T11+U11+V11
I12: =E12*F12 | J12: =E12*OT_MULT*G12 | K12: =I12+J12 | L12: =MIN(K12,MAX(0,SS_BASE-H12))*SS_PCT | M12: =K12*MED_PCT | N12: =MIN(K12,MAX(0,SINOT_BASE-H12))*SINOT_PCT | O12: 0 | P12: =L12+M12+N12+O12 | Q12: =K12-P12 | R12: =MIN(K12,MAX(0,SS_BASE-H12))*SS_PCT | S12: =K12*MED_PCT | T12: =MIN(K12,MAX(0,UI_BASE-H12))*FUTA_PCT | U12: =MIN(K12,MAX(0,UI_BASE-H12))*SUTA_PCT | V12: =MIN(K12,MAX(0,SINOT_BASE-H12))*SINOT_PCT | W12: =K12+R12+S12+T12+U12+V12
I13: =E13*F13 | J13: =E13*OT_MULT*G13 | K13: =I13+J13 | L13: =MIN(K13,MAX(0,SS_BASE-H13))*SS_PCT | M13: =K13*MED_PCT | N13: =MIN(K13,MAX(0,SINOT_BASE-H13))*SINOT_PCT | O13: 0 | P13: =L13+M13+N13+O13 | Q13: =K13-P13 | R13: =MIN(K13,MAX(0,SS_BASE-H13))*SS_PCT | S13: =K13*MED_PCT | T13: =MIN(K13,MAX(0,UI_BASE-H13))*FUTA_PCT | U13: =MIN(K13,MAX(0,UI_BASE-H13))*SUTA_PCT | V13: =MIN(K13,MAX(0,SINOT_BASE-H13))*SINOT_PCT | W13: =K13+R13+S13+T13+U13+V13
I14: =E14*F14 | J14: =E14*OT_MULT*G14 | K14: =I14+J14 | L14: =MIN(K14,MAX(0,SS_BASE-H14))*SS_PCT | M14: =K14*MED_PCT | N14: =MIN(K14,MAX(0,SINOT_BASE-H14))*SINOT_PCT | O14: 0 | P14: =L14+M14+N14+O14 | Q14: =K14-P14 | R14: =MIN(K14,MAX(0,SS_BASE-H14))*SS_PCT | S14: =K14*MED_PCT | T14: =MIN(K14,MAX(0,UI_BASE-H14))*FUTA_PCT | U14: =MIN(K14,MAX(0,UI_BASE-H14))*SUTA_PCT | V14: =MIN(K14,MAX(0,SINOT_BASE-H14))*SINOT_PCT | W14: =K14+R14+S14+T14+U14+V14
I15: =E15*F15 | J15: =E15*OT_MULT*G15 | K15: =I15+J15 | L15: =MIN(K15,MAX(0,SS_BASE-H15))*SS_PCT | M15: =K15*MED_PCT | N15: =MIN(K15,MAX(0,SINOT_BASE-H15))*SINOT_PCT | O15: 0 | P15: =L15+M15+N15+O15 | Q15: =K15-P15 | R15: =MIN(K15,MAX(0,SS_BASE-H15))*SS_PCT | S15: =K15*MED_PCT | T15: =MIN(K15,MAX(0,UI_BASE-H15))*FUTA_PCT | U15: =MIN(K15,MAX(0,UI_BASE-H15))*SUTA_PCT | V15: =MIN(K15,MAX(0,SINOT_BASE-H15))*SINOT_PCT | W15: =K15+R15+S15+T15+U15+V15
I16: =E16*F16 | J16: =E16*OT_MULT*G16 | K16: =I16+J16 | L16: =MIN(K16,MAX(0,SS_BASE-H16))*SS_PCT | M16: =K16*MED_PCT | N16: =MIN(K16,MAX(0,SINOT_BASE-H16))*SINOT_PCT | O16: 0 | P16: =L16+M16+N16+O16 | Q16: =K16-P16 | R16: =MIN(K16,MAX(0,SS_BASE-H16))*SS_PCT | S16: =K16*MED_PCT | T16: =MIN(K16,MAX(0,UI_BASE-H16))*FUTA_PCT | U16: =MIN(K16,MAX(0,UI_BASE-H16))*SUTA_PCT | V16: =MIN(K16,MAX(0,SINOT_BASE-H16))*SINOT_PCT | W16: =K16+R16+S16+T16+U16+V16
I17: =E17*F17 | J17: =E17*OT_MULT*G17 | K17: =I17+J17 | L17: =MIN(K17,MAX(0,SS_BASE-H17))*SS_PCT | M17: =K17*MED_PCT | N17: =MIN(K17,MAX(0,SINOT_BASE-H17))*SINOT_PCT | O17: 0 | P17: =L17+M17+N17+O17 | Q17: =K17-P17 | R17: =MIN(K17,MAX(0,SS_BASE-H17))*SS_PCT | S17: =K17*MED_PCT | T17: =MIN(K17,MAX(0,UI_BASE-H17))*FUTA_PCT | U17: =MIN(K17,MAX(0,UI_BASE-H17))*SUTA_PCT | V17: =MIN(K17,MAX(0,SINOT_BASE-H17))*SINOT_PCT | W17: =K17+R17+S17+T17+U17+V17
I18: =E18*F18 | J18: =E18*OT_MULT*G18 | K18: =I18+J18 | L18: =MIN(K18,MAX(0,SS_BASE-H18))*SS_PCT | M18: =K18*MED_PCT | N18: =MIN(K18,MAX(0,SINOT_BASE-H18))*SINOT_PCT | O18: 0 | P18: =L18+M18+N18+O18 | Q18: =K18-P18 | R18: =MIN(K18,MAX(0,SS_BASE-H18))*SS_PCT | S18: =K18*MED_PCT | T18: =MIN(K18,MAX(0,UI_BASE-H18))*FUTA_PCT | U18: =MIN(K18,MAX(0,UI_BASE-H18))*SUTA_PCT | V18: =MIN(K18,MAX(0,SINOT_BASE-H18))*SINOT_PCT | W18: =K18+R18+S18+T18+U18+V18
A19: TOTALES | I19: =SUM(I4:I18) | J19: =SUM(J4:J18) | K19: =SUM(K4:K18) | L19: =SUM(L4:L18) | M19: =SUM(M4:M18) | N19: =SUM(N4:N18) | O19: =SUM(O4:O18) | P19: =SUM(P4:P18) | ... W19: =SUM(W4:W18)

Sheet Contratistas 1099
A1: REGISTRO DE PAGOS — CONTRATISTAS 1099
A2: Retención 10% sobre servicios (Hacienda). Primeros $500/año exentos. 'Relevo total = S' → 0% retención.
A3: Contratista | B3: ID/EIN | C3: Servicio prestado | D3: Relevo total (S/N) | E3: Pago bruto período | F3: Pagos YTD anterior | G3: Base sujeta a retención | H3: Retención 10% | I3: NETO A PAGAR | J3: Formulario informativo
A4: Servicios Contables LM (EJEMPLO) | B4: 66-1234567 | C4: Contabilidad mensual | D4: N | E4: 800 | F4: 0 | G4: =IF(UPPER(D4)="S",0,MAX(0,E4-MAX(0,EXEN_1099-F4))) | H4: =G4*RET_1099 | I4: =E4-H4 | J4: =IF(UPPER(D4)="S","480.6D (exento)","480.6SP / 480.6A")
A5: Diseño Web PR (EJEMPLO) | B5: 66-7654321 | C5: Página web | D5: N | E5: 450 | F5: 0 | G5: =IF(UPPER(D5)="S",0,MAX(0,E5-MAX(0,EXEN_1099-F5))) | H5: =G5*RET_1099 | I5: =E5-H5 | J5: =IF(UPPER(D5)="S","480.6D (exento)","480.6SP / 480.6A")
A6: Consultor J. Ríos (EJEMPLO) | B6: 987-65-4321 | C6: Consultoría (relevo) | D6: S | E6: 1200 | F6: 0 | G6: =IF(UPPER(D6)="S",0,MAX(0,E6-MAX(0,EXEN_1099-F6))) | H6: =G6*RET_1099 | I6: =E6-H6 | J6: =IF(UPPER(D6)="S","480.6D (exento)","480.6SP / 480.6A")
G7: =IF(UPPER(D7)="S",0,MAX(0,E7-MAX(0,EXEN_1099-F7))) | H7: =G7*RET_1099 | I7: =E7-H7 | J7: =IF(UPPER(D7)="S","480.6D (exento)","480.6SP / 480.6A")
G8: =IF(UPPER(D8)="S",0,MAX(0,E8-MAX(0,EXEN_1099-F8))) | H8: =G8*RET_1099 | I8: =E8-H8 | J8: =IF(UPPER(D8)="S","480.6D (exento)","480.6SP / 480.6A")
G9: =IF(UPPER(D9)="S",0,MAX(0,E9-MAX(0,EXEN_1099-F9))) | H9: =G9*RET_1099 | I9: =E9-H9 | J9: =IF(UPPER(D9)="S","480.6D (exento)","480.6SP / 480.6A")
G10: =IF(UPPER(D10)="S",0,MAX(0,E10-MAX(0,EXEN_1099-F10))) | H10: =G10*RET_1099 | I10: =E10-H10 | J10: =IF(UPPER(D10)="S","480.6D (exento)","480.6SP / 480.6A")
G11: =IF(UPPER(D11)="S",0,MAX(0,E11-MAX(0,EXEN_1099-F11))) | H11: =G11*RET_1099 | I11: =E11-H11 | J11: =IF(UPPER(D11)="S","480.6D (exento)","480.6SP / 480.6A")
G12: =IF(UPPER(D12)="S",0,MAX(0,E12-MAX(0,EXEN_1099-F12))) | H12: =G12*RET_1099 | I12: =E12-H12 | J12: =IF(UPPER(D12)="S","480.6D (exento)","480.6SP / 480.6A")
G13: =IF(UPPER(D13)="S",0,MAX(0,E13-MAX(0,EXEN_1099-F13))) | H13: =G13*RET_1099 | I13: =E13-H13 | J13: =IF(UPPER(D13)="S","480.6D (exento)","480.6SP / 480.6A")
G14: =IF(UPPER(D14)="S",0,MAX(0,E14-MAX(0,EXEN_1099-F14))) | H14: =G14*RET_1099 | I14: =E14-H14 | J14: =IF(UPPER(D14)="S","480.6D (exento)","480.6SP / 480.6A")
G15: =IF(UPPER(D15)="S",0,MAX(0,E15-MAX(0,EXEN_1099-F15))) | H15: =G15*RET_1099 | I15: =E15-H15 | J15: =IF(UPPER(D15)="S","480.6D (exento)","480.6SP / 480.6A")
A16: TOTALES | E16: =SUM(E4:E15) | G16: =SUM(G4:G15) | H16: =SUM(H4:H15) | I16: =SUM(I4:I15)

Sheet Bono Navidad
A1: CÁLCULO DEL BONO DE NAVIDAD — Ley 148 (enm. Ley 4-2017)
A2: Pago obligatorio entre 15-nov y 15-dic. 6% si patrono >15 empleados (tope salario $10,000 → máx $600).
A3: Empleado | B3: Fecha ingreso | C3: Horas trabajadas (1-oct a 30-sep) | D3: Salario devengado en el período | E3: ¿Cualifica? (≥1,350h) | F3: % aplicado | G3: BONO A PAGAR
A4: María Rodríguez (EJEMPLO) | B4: 2023-03-01 | C4: 1800 | D4: 28000 | E4: =IF(C4="","",IF(C4>=BONO_HRS,"Sí","No")) | F4: =IF(E4="Sí",BONO_PCT_G,0) | G4: =IF(E4="Sí",MIN(D4,BONO_TOPE)*BONO_PCT_G,0)
A5: José Torres (EJEMPLO) | B5: 2021-07-15 | C5: 1600 | D5: 21000 | E5: =IF(C5="","",IF(C5>=BONO_HRS,"Sí","No")) | F5: =IF(E5="Sí",BONO_PCT_G,0) | G5: =IF(E5="Sí",MIN(D5,BONO_TOPE)*BONO_PCT_G,0)
A6: Ana Vega (EJEMPLO) | B6: 2024-01-10 | C6: 1200 | D6: 12600 | E6: =IF(C6="","",IF(C6>=BONO_HRS,"Sí","No")) | F6: =IF(E6="Sí",BONO_PCT_G,0) | G6: =IF(E6="Sí",MIN(D6,BONO_TOPE)*BONO_PCT_G,0)
E7: =IF(C7="","",IF(C7>=BONO_HRS,"Sí","No")) | F7: =IF(E7="Sí",BONO_PCT_G,0) | G7: =IF(E7="Sí",MIN(D7,BONO_TOPE)*BONO_PCT_G,0)
E8: =IF(C8="","",IF(C8>=BONO_HRS,"Sí","No")) | F8: =IF(E8="Sí",BONO_PCT_G,0) | G8: =IF(E8="Sí",MIN(D8,BONO_TOPE)*BONO_PCT_G,0)
E9: =IF(C9="","",IF(C9>=BONO_HRS,"Sí","No")) | F9: =IF(E9="Sí",BONO_PCT_G,0) | G9: =IF(E9="Sí",MIN(D9,BONO_TOPE)*BONO_PCT_G,0)
E10: =IF(C10="","",IF(C10>=BONO_HRS,"Sí","No")) | F10: =IF(E10="Sí",BONO_PCT_G,0) | G10: =IF(E10="Sí",MIN(D10,BONO_TOPE)*BONO_PCT_G,0)
E11: =IF(C11="","",IF(C11>=BONO_HRS,"Sí","No")) | F11: =IF(E11="Sí",BONO_PCT_G,0) | G11: =IF(E11="Sí",MIN(D11,BONO_TOPE)*BONO_PCT_G,0)
E12: =IF(C12="","",IF(C12>=BONO_HRS,"Sí","No")) | F12: =IF(E12="Sí",BONO_PCT_G,0) | G12: =IF(E12="Sí",MIN(D12,BONO_TOPE)*BONO_PCT_G,0)
E13: =IF(C13="","",IF(C13>=BONO_HRS,"Sí","No")) | F13: =IF(E13="Sí",BONO_PCT_G,0) | G13: =IF(E13="Sí",MIN(D13,BONO_TOPE)*BONO_PCT_G,0)
E14: =IF(C14="","",IF(C14>=BONO_HRS,"Sí","No")) | F14: =IF(E14="Sí",BONO_PCT_G,0) | G14: =IF(E14="Sí",MIN(D14,BONO_TOPE)*BONO_PCT_G,0)
E15: =IF(C15="","",IF(C15>=BONO_HRS,"Sí","No")) | F15: =IF(E15="Sí",BONO_PCT_G,0) | G15: =IF(E15="Sí",MIN(D15,BONO_TOPE)*BONO_PCT_G,0)
E16: =IF(C16="","",IF(C16>=BONO_HRS,"Sí","No")) | F16: =IF(E16="Sí",BONO_PCT_G,0) | G16: =IF(E16="Sí",MIN(D16,BONO_TOPE)*BONO_PCT_G,0)
E17: =IF(C17="","",IF(C17>=BONO_HRS,"Sí","No")) | F17: =IF(E17="Sí",BONO_PCT_G,0) | G17: =IF(E17="Sí",MIN(D17,BONO_TOPE)*BONO_PCT_G,0)
E18: =IF(C18="","",IF(C18>=BONO_HRS,"Sí","No")) | F18: =IF(E18="Sí",BONO_PCT_G,0) | G18: =IF(E18="Sí",MIN(D18,BONO_TOPE)*BONO_PCT_G,0)
A19: TOTAL BONO | D19: =SUM(D4:D18) | G19: =SUM(G4:G18)

Sheet Resumen y Cumplimiento
A1: RESUMEN DEL PERÍODO Y LISTA DE CUMPLIMIENTO
A2: Empresas HC LLC · Puerto Rico · Consolida nómina W-2, contratistas 1099 y obligaciones legales.
A4: RESUMEN FINANCIERO DEL PERÍODO
A5: Bruto total empleados W-2 | D5: ='Nómina W-2'!K19
A6: Neto total a pagar (W-2) | D6: ='Nómina W-2'!Q19
A7: Retención PR empleados (499R) | D7: ='Nómina W-2'!O19
A8: Total deducciones empleados | D8: ='Nómina W-2'!P19
A9: Costo patronal total (W-2) | D9: ='Nómina W-2'!W19
A10: Pagos brutos a contratistas 1099 | D10: ='Contratistas 1099'!E16
A11: Retención 10% a contratistas | D11: ='Contratistas 1099'!H16
A12: Neto a pagar contratistas | D12: ='Contratistas 1099'!I16
A13: Provisión Bono de Navidad (anual) | D13: ='Bono Navidad'!G19
A15: LISTA DE CUMPLIMIENTO LEGAL — PUERTO RICO
A16: ✓ | B16: Obligación | C16: Base legal / Formulario | D16: Frecuencia
A17: ☐ | B17: Pagar salario mínimo ≥ $10.50/h | C17: Ley 47-2021 | D17: Cada nómina
A18: ☐ | B18: Horas extra a 2x (>8h/día ó >40h/sem) | C18: Ley 379-1948 | D18: Cada nómina
A19: ☐ | B19: Retener y depositar Seg. Social + Medicare | C19: FICA / Form. 941-PR | D19: Cada depósito
A20: ☐ | B20: Retener contribución sobre ingresos (PR) | C20: Form. 499R-1B / 499R-2 | D20: Mensual/quincenal
A21: ☐ | B21: Pagar SINOT (0.3% patrono + 0.3% empleado) | C21: DTRH / SINOT | D21: Trimestral
A22: ☐ | B22: Pagar Seguro por Desempleo (FUTA+SUTA) | C22: Form. 940 / PR UI | D22: Trimestral
A23: ☐ | B23: Póliza CFSE (Fondo del Seguro del Estado) | C23: Ley 45 / CFSE | D23: Anual
A24: ☐ | B24: Seguro Choferil (si hay conductores) | C24: DTRH | D24: Según aplique
A25: ☐ | B25: Retener 10% a contratistas por servicios | C25: Hacienda / 480.6 | D25: Cada pago
A26: ☐ | B26: Emitir W-2PR (499R-2) a empleados | C26: Hacienda | D26: Anual (31-ene)
A27: ☐ | B27: Emitir 480.6 a contratistas | C27: Hacienda | D27: Anual
... A30: ☐ | B30: Conservar registros de nómina | C30: Ley 379 / FLSA | D30: ≥ 3 años
A32: AVISO: Plantilla de apoyo. Las tasas (base SS, tasa SUTA asignada, tablas de retención 499R) cambian y deben verificarse con el Departamento de Hacienda y el DTRH para cada período. No sustituye asesoría legal o contributiva profesional.
